README.md
setup.py
splitter/__init__.py
splitter/image_preprocessing.py
splitter/model.py
splitter/prediction_utils.py
victor_services_splitter.egg-info/PKG-INFO
victor_services_splitter.egg-info/SOURCES.txt
victor_services_splitter.egg-info/dependency_links.txt
victor_services_splitter.egg-info/requires.txt
victor_services_splitter.egg-info/top_level.txt