Metadata-Version: 2.1
Name: victor-services-splitter
Version: 0.1.1
Summary: Model to automatize the separation of a messy PDF into multiple documents for the Brazilian Federal Supreme Court.
Home-page: https://gitlab.com/gpam/victor/SERVICES/splitter
Author: Ailab
Author-email: ailabunb@gmail.com
License: UNKNOWN
Platform: UNKNOWN
Classifier: Programming Language :: Python :: 3
Classifier: Operating System :: OS Independent
Requires-Python: >=3.6
